setup.py
wsadipkgnew/__init__.py
wsadipkgnew/calculator.py
wsadipkgnew.egg-info/PKG-INFO
wsadipkgnew.egg-info/SOURCES.txt
wsadipkgnew.egg-info/dependency_links.txt
wsadipkgnew.egg-info/top_level.txt